expressly/__init__.py
expressly/api.py
expressly/api_responses.py
expressly/errors.py
expressly/models.py
expressly/provider.py
expressly/resources.py
expressly/route_responses.py
expressly/routes.py
expressly-2.0.1.dist-info/DESCRIPTION.rst
expressly-2.0.1.dist-info/METADATA
expressly-2.0.1.dist-info/metadata.json
expressly-2.0.1.dist-info/RECORD
expressly-2.0.1.dist-info/top_level.txt
expressly-2.0.1.dist-info/WHEEL
