Metadata-Version: 2.0
Name: expressly
Version: 2.0.1
Summary: Expressly Python 3 SDK
Home-page: https://github.com/expressly/python-sdk
Author: Expressly
Author-email: info@buyexpressly.com
License: UNKNOWN
Platform: UNKNOWN
Requires: simplejson
